cefeste/__init__.py
cefeste/config.py
cefeste/custom_extension.py
cefeste/utils.py
cefeste/elimination/__init__.py
cefeste/elimination/shap_rfe.py
cefeste/selection/__init__.py
cefeste/selection/explanatory.py
cefeste/selection/multivariate.py
cefeste/selection/univariate.py
cefeste/transform/__init__.py
cefeste-2.0.0.dist-info/.ipynb_checkpoints/PKG-INFO-checkpoint
cefeste-2.0.0.dist-info/.ipynb_checkpoints/dependency_links-checkpoint.txt
cefeste-2.0.0.dist-info/licenses/LICENCE
cefeste-2.0.0.dist-info/METADATA
cefeste-2.0.0.dist-info/WHEEL
cefeste-2.0.0.dist-info/top_level.txt
cefeste-2.0.0.dist-info/RECORD
