Metadata-Version: 2.4
Name: cefeste
Version: 2.0.0
Summary: Feature Selection and Elimination
Home-page: https://dev.azure.com/credem-data/DAT/_git/ce-feste
Author: DAT Team
Project-URL: Homepage, https://dev.azure.com/credem-data/DAT/_git/ce-feste
Classifier: Programming Language :: Python :: 3
Classifier: License :: OSI Approved :: MIT License
Classifier: Operating System :: OS Independent
Requires-Python: >=3.9, <4
License-File: LICENCE
Requires-Dist: typed-ast>=1.5.4
Requires-Dist: numpy==1.22.4
Requires-Dist: pandas>=1.4.2
Requires-Dist: scikit-learn>=1.1.1
Requires-Dist: scipy>=1.8.1
Requires-Dist: statsmodels>=0.13.2
Requires-Dist: PyYAML>=6.0
Requires-Dist: shap==0.41.0
Requires-Dist: ipython
Dynamic: home-page
Dynamic: license-file
Dynamic: requires-python
